corecon/DataEntryClass.py
corecon/FieldClass.py
corecon/InternalFunctions.py
corecon/__init__.py
corecon/check_updates.py
corecon/fields_info.py
corecon/loaders.py
corecon/version.py
corecon/data/__init__.py
corecon/data/data_entry_template.py
corecon/data/make_data_archive.py
corecon/data/HII_fraction/Bolton_et_al_2011.py
corecon/data/HII_fraction/Bosman_et_al_2022.py
corecon/data/HII_fraction/Chornock_et_al_2013.py
corecon/data/HII_fraction/Choudhury_et_al_2015.py
corecon/data/HII_fraction/Choudhury_et_al_2021.py
corecon/data/HII_fraction/Davies_et_al_2018.py
corecon/data/HII_fraction/Dijkstra_et_al_2011.py
corecon/data/HII_fraction/Durovcikova_et_al_2024.py
corecon/data/HII_fraction/Fan_et_al_2006.py
corecon/data/HII_fraction/Gaikwad_et_al_2023.py
corecon/data/HII_fraction/Greig_et_al_2017.py
corecon/data/HII_fraction/Greig_et_al_2019.py
corecon/data/HII_fraction/Hoag_et_al_2019.py
corecon/data/HII_fraction/Jensen_et_al_2013.py
corecon/data/HII_fraction/Jung_et_al_2020.py
corecon/data/HII_fraction/Lu_et_al_2020.py
corecon/data/HII_fraction/Mason_et_al_2018.py
corecon/data/HII_fraction/Mason_et_al_2019.py
corecon/data/HII_fraction/McGreer_et_al_2011.py
corecon/data/HII_fraction/McGreer_et_al_2015.py
corecon/data/HII_fraction/Mesinger_et_al_2015.py
corecon/data/HII_fraction/Mortlock_et_al_2011.py
corecon/data/HII_fraction/Nakane_et_al_2024.py
corecon/data/HII_fraction/Ono_et_al_2012.py
corecon/data/HII_fraction/Ota_et_al_2008.py
corecon/data/HII_fraction/Ouchi_et_al_2010.py
corecon/data/HII_fraction/Pentericci_et_al_2014.py
corecon/data/HII_fraction/Robertson_et_al_2013.py
corecon/data/HII_fraction/Schenker_et_al_2014.py
corecon/data/HII_fraction/Schroeder_et_al_2013.py
corecon/data/HII_fraction/Sobacchi_Mesinger_2015.py
corecon/data/HII_fraction/Spina_et_al_2024.py
corecon/data/HII_fraction/Tilvi_et_al_2014.py
corecon/data/HII_fraction/Totani_et_al_2006.py
corecon/data/HII_fraction/Umeda_et_al_2023.py
corecon/data/HII_fraction/Wang_et_al_2020.py
corecon-1.4.3.dist-info/LICENSE.txt
corecon-1.4.3.dist-info/METADATA
corecon-1.4.3.dist-info/WHEEL
corecon-1.4.3.dist-info/top_level.txt
corecon-1.4.3.dist-info/RECORD
