Metadata-Version: 2.1
Name: corecon
Version: 1.4.3
Summary: an open collection of constraints on the Epoch of Reionization
Home-page: https://github.com/EGaraldi/corecon
Download-URL: https://github.com/EGaraldi/corecon/archive/v1.4.3.tar.gz
Author: Enrico Garaldi
Author-email: enrico.garaldi@gmail.com
License: gpl-3.0
Keywords: constraints,reionization,cosmic,observations,data
Classifier: Development Status :: 5 - Production/Stable
Classifier: Intended Audience :: Science/Research
Classifier: Topic :: Software Development :: Build Tools
Classifier: Topic :: Scientific/Engineering :: Astronomy
Classifier: License :: OSI Approved :: GNU General Public License v3 or later (GPLv3+)
Classifier: Programming Language :: Python :: 3
Classifier: Programming Language :: Python :: 3.4
Classifier: Programming Language :: Python :: 3.5
Classifier: Programming Language :: Python :: 3.6
Classifier: Programming Language :: Python :: 3.7
Classifier: Programming Language :: Python :: 3.8
Classifier: Programming Language :: Python :: 3.9
Classifier: Programming Language :: Python :: 3.10
Classifier: Programming Language :: Python :: 3.11
Classifier: Programming Language :: Python :: 3.12
License-File: LICENSE.txt
Requires-Dist: numpy
